pygeoglim/__init__.py
pygeoglim/glhymps.py
pygeoglim/glim.py
pygeoglim/utils.py
pygeoglim-1.0.7.dist-info/licenses/LICENSE
pygeoglim-1.0.7.dist-info/METADATA
pygeoglim-1.0.7.dist-info/WHEEL
pygeoglim-1.0.7.dist-info/top_level.txt
pygeoglim-1.0.7.dist-info/RECORD
