Metadata-Version: 2.4
Name: pygeoglim
Version: 1.0.7
Summary: A Python package for extracting geological attributes from GLiM and GLHYMPS datasets
Author: Mohammad Galib
Author-email: Mohammad Galib <mgalib@purdue.edu>
License: MIT
Project-URL: Homepage, https://github.com/galib9690/pygeoglim
Project-URL: Repository, https://github.com/galib9690/pygeoglim.git
Project-URL: Issues, https://github.com/galib9690/pygeoglim/issues
Project-URL: Documentation, https://github.com/galib9690/pygeoglim#readme
Keywords: geology,hydrology,watershed,GLiM,GLHYMPS,geospatial
Classifier: Development Status :: 5 - Production/Stable
Classifier: Intended Audience :: Science/Research
Classifier: Topic :: Scientific/Engineering :: GIS
Classifier: License :: OSI Approved :: MIT License
Classifier: Programming Language :: Python :: 3
Classifier: Programming Language :: Python :: 3.8
Classifier: Programming Language :: Python :: 3.9
Classifier: Programming Language :: Python :: 3.10
Classifier: Programming Language :: Python :: 3.11
Classifier: Programming Language :: Python :: 3.12
Requires-Python: >=3.8
License-File: LICENSE
Requires-Dist: geopandas>=0.12.0
Requires-Dist: shapely>=1.8.0
Requires-Dist: numpy>=1.20.0
Requires-Dist: pandas>=1.3.0
Dynamic: author
Dynamic: license-file
Dynamic: requires-python
